{
  "name": "Events App",
  "short_name": "Events",
  "description": "Application mobile pour découvrir et s'inscrire aux événements",
  "start_url": "/",
  "display": "standalone",
  "background_color": "#ffffff",
  "theme_color": "#000000",
  "orientation": "portrait",
  "scope": "/",
  "icons": [
    {
      "src": "/icon-192.png",
      "sizes": "192x192",
      "type": "image/png",
      "purpose": "any"
    }
  ],
  "categories": ["entertainment", "social"],
  "screenshots": [
    {
      "src": "/screenshot-mobile.png",
      "sizes": "375x667",
      "type": "image/png",
      "form_factor": "narrow"
    }
  ]
}
